pynwheel/__init__.py
pynwheel/api.py
pynwheel/enums.py
pynwheel/request_handler.py
pynwheel/utils.py
pynwheel/models/Account.py
pynwheel/models/Address.py
pynwheel/models/Deduction.py
pynwheel/models/DirectDepositAllocations.py
pynwheel/models/Earning.py
pynwheel/models/Employer.py
pynwheel/models/Employment.py
pynwheel/models/Identity.py
pynwheel/models/Income.py
pynwheel/models/Job.py
pynwheel/models/Paystub.py
pynwheel/models/Phone.py
pynwheel/models/Platform.py
pynwheel/models/SearchResult.py
pynwheel/models/Shift.py
pynwheel/models/ShiftTimestamp.py
pynwheel/models/Site.py
pynwheel/models/Tax.py
pynwheel/models/Webhook.py
pynwheel/models/WebhookPostBody.py
pynwheel/models/__init__.py
pynwheel-0.1.0.dist-info/LICENSE
pynwheel-0.1.0.dist-info/METADATA
pynwheel-0.1.0.dist-info/WHEEL
pynwheel-0.1.0.dist-info/top_level.txt
pynwheel-0.1.0.dist-info/RECORD
